sql_idempotent_tool/__init__.py
sql_idempotent_tool/cli.py
sql_idempotent_tool/config.py
sql_idempotent_tool/formatter.py
sql_idempotent_tool/sql_parser.py
sql_idempotent_tool-0.1.0.dist-info/METADATA
sql_idempotent_tool-0.1.0.dist-info/WHEEL
sql_idempotent_tool-0.1.0.dist-info/entry_points.txt
sql_idempotent_tool-0.1.0.dist-info/licenses/LICENSE
sql_idempotent_tool-0.1.0.dist-info/RECORD
