Metadata-Version: 2.4
Name: sql-idempotent-tool
Version: 0.1.0
Summary: A CLI tool to add idempotent statements to SQL files
Project-URL: Homepage, https://github.com/openinvestapp/sql-idempotent-tool
Project-URL: Repository, https://github.com/openinvestapp/sql-idempotent-tool
Project-URL: Issues, https://github.com/openinvestapp/sql-idempotent-tool/issues
Project-URL: Documentation, https://github.com/openinvestapp/sql-idempotent-tool#readme
Author-email: OpenInvest <dev@openinvest.com>
Maintainer-email: OpenInvest <dev@openinvest.com>
License: MIT
License-File: LICENSE
Keywords: database,idempotent,migration,mysql,postgresql,sql
Classifier: Development Status :: 4 - Beta
Classifier: Intended Audience :: Developers
Classifier: License :: OSI Approved :: MIT License
Classifier: Operating System :: OS Independent
Classifier: Programming Language :: Python :: 3
Classifier: Programming Language :: Python :: 3.12
Classifier: Topic :: Database
Classifier: Topic :: Software Development :: Libraries :: Python Modules
Classifier: Topic :: Utilities
Requires-Python: >=3.12
Requires-Dist: click>=8.0.0
Requires-Dist: pydantic>=2.0.0
Requires-Dist: rich>=13.0.0
Requires-Dist: sqlfluff>=3.4.1
Requires-Dist: toml>=0.10.0
Requires-Dist: tree-sitter-sql>=0.3.0
Requires-Dist: tree-sitter>=0.20.0
Requires-Dist: typer>=0.9.0
